strangeworks_qiskit/__init__.py
strangeworks_qiskit/_runtime_client.py
strangeworks_qiskit/backends/__init__.py
strangeworks_qiskit/backends/_utils.py
strangeworks_qiskit/backends/aws.py
strangeworks_qiskit/backends/honeywell.py
strangeworks_qiskit/backends/ibm.py
strangeworks_qiskit/backends/ionq.py
strangeworks_qiskit/backends/rigetti.py
strangeworks_qiskit/backends/strangeworks.py
strangeworks_qiskit/jobs/__init__.py
strangeworks_qiskit/jobs/ibm.py
strangeworks_qiskit/jobs/job.py
strangeworks_qiskit/jobs/status.py
strangeworks_qiskit/platform/__init__.py
strangeworks_qiskit/platform/backends.py
strangeworks_qiskit/provider.py
strangeworks_qiskit/runtimes.py
strangeworks_qiskit-0.4.7.dist-info/LICENSE
strangeworks_qiskit-0.4.7.dist-info/METADATA
strangeworks_qiskit-0.4.7.dist-info/WHEEL
strangeworks_qiskit-0.4.7.dist-info/RECORD
