Metadata-Version: 2.1
Name: strangeworks-qiskit
Version: 0.4.7
Summary: Strangeworks Qiskit SDK Extension
License: Apache-2.0
Author: Strange Devs
Author-email: hello@strangeworks.com
Requires-Python: >=3.10,<4.0
Classifier: License :: OSI Approved :: Apache Software License
Classifier: Programming Language :: Python :: 3
Classifier: Programming Language :: Python :: 3.10
Classifier: Programming Language :: Python :: 3.11
Classifier: Programming Language :: Python :: 3.12
Requires-Dist: qiskit (==0.40.0)
Requires-Dist: strangeworks (>=0.5.1,<0.6.0)
Requires-Dist: strangeworks-core (>=0.3.6,<0.4.0)
